contigion_utils/__init__.py
contigion_utils/log.py
contigion_utils/print.py
contigion_utils-1.0.5.dist-info/METADATA
contigion_utils-1.0.5.dist-info/WHEEL
contigion_utils-1.0.5.dist-info/top_level.txt
contigion_utils-1.0.5.dist-info/RECORD
