Metadata-Version: 2.1
Name: contigion-utils
Version: 1.0.5
Summary: A library for utility functions common across Contigion projects
Author-email: Contigion <contigion@gmail.com>
Classifier: Programming Language :: Python :: 3.12
Classifier: Operating System :: OS Independent
